shufflemates/__init__.py
shufflemates/main.py
shufflemates-0.1.2.dist-info/METADATA
shufflemates-0.1.2.dist-info/WHEEL
shufflemates-0.1.2.dist-info/top_level.txt
shufflemates-0.1.2.dist-info/RECORD
