Metadata-Version: 2.1
Name: shufflemates
Version: 0.1.2
Summary: A Python package for randomly grouping students or teams.
Home-page: https://github.com/ianolpx/shufflemates
Author: Ian Park
Author-email: Ian Park <ianolpx@gmail.com>
Classifier: Programming Language :: Python :: 3
Classifier: License :: OSI Approved :: MIT License
Classifier: Operating System :: OS Independent
Requires-Python: >=3.6
